WhisperDriver/__init__.py
WhisperDriver/wrapper.py
WhisperDriver/Obj/__init__.py
WhisperDriver/Obj/bots.py
WhisperDriver/Obj/endpoints.py
WhisperDriver/Obj/scheduler.py
WhisperDriver/Obj/throttle.py
WhisperDriver/Obj/variables.py
WhisperDriver/Obj/via_ui.py
WhisperDriver/utils/__init__.py
WhisperDriver/utils/time.py
WhisperDriver-0.1.8.dist-info/METADATA
WhisperDriver-0.1.8.dist-info/WHEEL
WhisperDriver-0.1.8.dist-info/top_level.txt
WhisperDriver-0.1.8.dist-info/RECORD
