Metadata-Version: 2.1
Name: WhisperDriver
Version: 0.1.8
Summary: Automation and API library for WhisperTrades.com
Home-page: https://github.com/PaulNobrega/WhisperDriver
Author: Paul Nobrega
Author-email: Paul@PaulNobrega.net
License: MIT
Platform: UNKNOWN
Classifier: Programming Language :: Python :: 3
Classifier: License :: OSI Approved :: MIT License
Classifier: Operating System :: OS Independent
Requires-Python: >=3.10
Requires-Dist: APScheduler
Requires-Dist: pathlib
Requires-Dist: beautifulsoup4
Requires-Dist: undetected-chromedriver (>=3.5.5)
Requires-Dist: lxml
Requires-Dist: numpy
Requires-Dist: requests
Requires-Dist: requests-toolbelt
Requires-Dist: selenium (>=4.21.0)
Requires-Dist: soupsieve
Requires-Dist: tzdata
Requires-Dist: tzlocal
Requires-Dist: urllib3
Requires-Dist: webencodings
Requires-Dist: websockets
Requires-Dist: wsproto
Requires-Dist: chromedriver-autoinstaller (>=0.6.4)
Requires-Dist: pandas
Requires-Dist: html5lib
Requires-Dist: schedule (==1.2.1)
Requires-Dist: python-dateutil (>=2.9.0)
Requires-Dist: pytz (>=2024.1)
